{
    "group_state_fields": [
        "state",
        "status",
        "brightness",
        "level",
        "hue",
        "saturation",
        "color",
        "mode",
        "kelvin",
        "color_temp",
        "bulb_mode",
        "computed_color",
        "effect",
        "device_id",
        "group_id",
        "device_type"
    ],
    "device_name": "Test",
    "admin_username": "",
    "admin_password": "",
    "http_repeat_factor": "10",
    "discovery_port": "8899",
    "listen_repeats": "3",
    "hostname": "",
    "static_ip": "",
    "static_mask": "0.0.0.0",
    "static_gate": "0.0.0.0",
    "ce_pin": "16",
    "csn_pin": "15",
    "reset_pin": "0",
    "led_pin": "-2",
    "auto_restart_period": "0",
    "state_flush_interval": "10",
    "led_mode_wifi_config": "Fast toggle",
    "led_mode_wifi_failed": "On",
    "led_mode_operating": "Off",
    "led_mode_packet": "Flicker",
    "led_mode_packet_count": "3",
    "packet_repeats": "20",
    "radio_interface_type": "nRF24",
    "packet_repeat_throttle_threshold": "200",
    "packet_repeat_throttle_sensitivity": "0",
    "packet_repeat_minimum": "3",
    "enable_automatic_mode_switching": "true",
    "mqtt_server": "192.168.178.14:1883",
    "mqtt_topic_pattern": "destinyMqtt/milight/:device_id/:device_type/:group_id",
    "mqtt_update_topic_pattern": "destinyMqtt/milight/adj/:device_id/:device_type/:group_id",
    "mqtt_state_topic_pattern": "destinyMqtt/milight/is/:device_id/:device_type/:group_id",
    "mqtt_sensor_topic_pattern": "destinyMqtt/milight/master/sensors/:sensor_type",
    "mqtt_client_id": "destinyMqttLightMaster",
    "mqtt_username": "destinyMqttLightMaster",
    "mqtt_password": "mqttlight@KA27",
    "mqtt_state_rate_limit": "50",
    "ota_password": "",
    "sda_pin": "4",
    "scl_pin": "5",
    "mqtt_push_interval": "",
    "mqtt_pin_1": "12",
    "mqtt_pin_2": "0",
    "mqtt_pin_3": "0",
    "mqtt_pin_4": "14",
    "device_ids": [
        7223,
        9005,
        10521,
        68,
        24737,
        26235
    ]
}